pandorafits/__init__.py
pandorafits/database/__init__.py
pandorafits/database/astrometry.py
pandorafits/database/convenience.py
pandorafits/database/level0.py
pandorafits/database/level1.py
pandorafits/database/level2.py
pandorafits/database/level3.py
pandorafits/database/mixins.py
pandorafits/database/targets.py
pandorafits/fits.py
pandorafits/formats/README.md
pandorafits/formats/engineering/level0-extension-types.xlsx
pandorafits/formats/engineering/level0-headers.xlsx
pandorafits/formats/level3/level3-extension-types.xlsx
pandorafits/formats/level3/level3-headers.xlsx
pandorafits/formats/nirda/level0_nirda.xlsx
pandorafits/formats/nirda/level1_nirda.xlsx
pandorafits/formats/nirda/level2_nirda.xlsx
pandorafits/formats/old/level0-ffi_nirda.xlsx
pandorafits/formats/old/level0-ffi_visda.xlsx
pandorafits/formats/old/level0_nirda.xlsx
pandorafits/formats/old/level0_nirda2.xlsx
pandorafits/formats/old/level0_visda.xlsx
pandorafits/formats/old/level1-ffi_visda.xlsx
pandorafits/formats/old/level1_visda.xlsx
pandorafits/formats/visda/level0-ffi_visda.xlsx
pandorafits/formats/visda/level0_visda.xlsx
pandorafits/formats/visda/level1-ffi_visda.xlsx
pandorafits/formats/visda/level1_visda.xlsx
pandorafits/formats/visda/level2-ffi_visda.xlsx
pandorafits/formats/visda/level2_visda.xlsx
pandorafits/formats.py
pandorafits/io.py
pandorafits/nirda.py
pandorafits/processing.py
pandorafits/report.py
pandorafits/reshape.py
pandorafits/roll.py
pandorafits/scene.py
pandorafits/utils.py
pandorafits/visda.py
pandorafits-0.4.4.dist-info/METADATA
pandorafits-0.4.4.dist-info/WHEEL
pandorafits-0.4.4.dist-info/RECORD
