Metadata-Version: 2.4
Name: pandorafits
Version: 0.4.4
Summary: Tools to work with fits files for Pandora
License: MIT
Author: Christina Hedges
Author-email: christina.l.hedges@nasa.gov
Requires-Python: >=3.9,<3.13
Classifier: License :: OSI Approved :: MIT License
Classifier: Programming Language :: Python :: 3
Classifier: Programming Language :: Python :: 3.9
Classifier: Programming Language :: Python :: 3.10
Classifier: Programming Language :: Python :: 3.11
Classifier: Programming Language :: Python :: 3.12
Requires-Dist: astropy (>=5)
Requires-Dist: lxml (>=5.3.0,<6.0.0)
Requires-Dist: openpyxl (>=3.1.5,<4.0.0)
Requires-Dist: pandas (>=2.2.2,<3.0.0)
Requires-Dist: pandoraaperture (>=0.1.14)
Requires-Dist: pandoraref (>=0.3.3)
Requires-Dist: sparse3d (>=1.2.11)
